argos_plugin_monitoring-0.1.0.dist-info/DESCRIPTION.rst
argos_plugin_monitoring-0.1.0.dist-info/METADATA
argos_plugin_monitoring-0.1.0.dist-info/RECORD
argos_plugin_monitoring-0.1.0.dist-info/WHEEL
argos_plugin_monitoring-0.1.0.dist-info/entry_points.txt
argos_plugin_monitoring-0.1.0.dist-info/metadata.json
argos_plugin_monitoring-0.1.0.dist-info/top_level.txt
monitoring/__init__.py
monitoring/__main__.py
monitoring/constants.py
monitoring/main.py
monitoring/checks/__init__.py
monitoring/checks/server_load.py
monitoring/checks/wordpress.py
