Metadata-Version: 2.0
Name: argos-plugin-monitoring
Version: 0.1.0
Summary: Argos plugin for monitoring
Home-page: https://github.com/Dundee/argos-plugin-monitoring
Author: Dundee
Author-email: daniel@milde.cz
License: GPL
Keywords: argos monitoring
Platform: UNKNOWN
Classifier: Programming Language :: Python
Classifier: Programming Language :: Python :: 2
Classifier: Programming Language :: Python :: 2.7
Classifier: Programming Language :: Python :: 3
Classifier: Programming Language :: Python :: 3.4
Classifier: License :: OSI Approved :: GNU General Public License v3 (GPLv3)
Classifier: Development Status :: 5 - Production/Stable
Classifier: Topic :: Internet :: WWW/HTTP :: Site Management
Classifier: Topic :: System :: Systems Administration
Classifier: Topic :: Utilities
Requires-Dist: wp-version-checker
